{
    "walls": [
        {
            "position": {
                "x": 5.892179489135742,
                "y": 3.0799999237060549
            },
            "health": 2,
            "blockScore": 4,
            "brickColor": {
                "r": 0.31132078170776369,
                "g": 0.054334286600351337,
                "b": 0.054334286600351337,
                "a": 1.0
            },
            "isDestroyed": false
        },
        {
            "position": {
                "x": 5.892179489135742,
                "y": 2.440000057220459
            },
            "health": 1,
            "blockScore": 3,
            "brickColor": {
                "r": 0.48349058628082278,
                "g": 0.040750715881586078,
                "b": 0.040750715881586078,
                "a": 1.0
            },
            "isDestroyed": false
        },
        {
            "position": {
                "x": 5.892179489135742,
                "y": 1.7999999523162842
            },
            "health": 0,
            "blockScore": 2,
            "brickColor": {
                "r": 0.6556603908538818,
                "g": 0.027167143300175668,
                "b": 0.027167143300175668,
                "a": 1.0
            },
            "isDestroyed": false
        },
        {
            "position": {
                "x": 5.892179489135742,
                "y": 1.159999966621399
            },
            "health": 1,
            "blockScore": 1,
            "brickColor": {
                "r": 0.8278301954269409,
                "g": 0.013583571650087834,
                "b": 0.013583571650087834,
                "a": 1.0
            },
            "isDestroyed": false
        },
        {
            "position": {
                "x": 4.601354598999023,
                "y": 3.0799999237060549
            },
            "health": 3,
            "blockScore": 4,
            "brickColor": {
                "r": 0.31132078170776369,
                "g": 0.054334286600351337,
                "b": 0.054334286600351337,
                "a": 1.0
            },
            "isDestroyed": false
        },
        {
            "position": {
                "x": 4.601354598999023,
                "y": 2.440000057220459
            },
            "health": 3,
            "blockScore": 3,
            "brickColor": {
                "r": 0.48349058628082278,
                "g": 0.040750715881586078,
                "b": 0.040750715881586078,
                "a": 1.0
            },
            "isDestroyed": false
        },
        {
            "position": {
                "x": 4.601354598999023,
                "y": 1.7999999523162842
            },
            "health": 2,
            "blockScore": 2,
            "brickColor": {
                "r": 0.6556603908538818,
                "g": 0.027167143300175668,
                "b": 0.027167143300175668,
                "a": 1.0
            },
            "isDestroyed": false
        },
        {
            "position": {
                "x": 4.601354598999023,
                "y": 1.159999966621399
            },
            "health": 1,
            "blockScore": 1,
            "brickColor": {
                "r": 0.8278301954269409,
                "g": 0.013583571650087834,
                "b": 0.013583571650087834,
                "a": 1.0
            },
            "isDestroyed": false
        },
        {
            "position": {
                "x": 4.601354598999023,
                "y": 0.5199999809265137
            },
            "health": 0,
            "blockScore": 0,
            "brickColor": {
                "r": 1.0,
                "g": 0.0,
                "b": 0.0,
                "a": 1.0
            },
            "isDestroyed": false
        },
        {
            "position": {
                "x": 3.3105297088623049,
                "y": 3.0799999237060549
            },
            "health": 4,
            "blockScore": 4,
            "brickColor": {
                "r": 0.31132078170776369,
                "g": 0.054334286600351337,
                "b": 0.054334286600351337,
                "a": 1.0
            },
            "isDestroyed": false
        },
        {
            "position": {
                "x": 3.3105297088623049,
                "y": 2.440000057220459
            },
            "health": 3,
            "blockScore": 3,
            "brickColor": {
                "r": 0.48349058628082278,
                "g": 0.040750715881586078,
                "b": 0.040750715881586078,
                "a": 1.0
            },
            "isDestroyed": false
        },
        {
            "position": {
                "x": 3.3105297088623049,
                "y": 1.7999999523162842
            },
            "health": 2,
            "blockScore": 2,
            "brickColor": {
                "r": 0.6556603908538818,
                "g": 0.027167143300175668,
                "b": 0.027167143300175668,
                "a": 1.0
            },
            "isDestroyed": false
        },
        {
            "position": {
                "x": 3.3105297088623049,
                "y": 1.159999966621399
            },
            "health": 1,
            "blockScore": 1,
            "brickColor": {
                "r": 0.8278301954269409,
                "g": 0.013583571650087834,
                "b": 0.013583571650087834,
                "a": 1.0
            },
            "isDestroyed": false
        },
        {
            "position": {
                "x": 2.0197043418884279,
                "y": 3.0799999237060549
            },
            "health": 2,
            "blockScore": 4,
            "brickColor": {
                "r": 0.31132078170776369,
                "g": 0.054334286600351337,
                "b": 0.054334286600351337,
                "a": 1.0
            },
            "isDestroyed": false
        },
        {
            "position": {
                "x": 2.0197043418884279,
                "y": 2.440000057220459
            },
            "health": 3,
            "blockScore": 3,
            "brickColor": {
                "r": 0.48349058628082278,
                "g": 0.040750715881586078,
                "b": 0.040750715881586078,
                "a": 1.0
            },
            "isDestroyed": false
        },
        {
            "position": {
                "x": 2.0197043418884279,
                "y": 1.7999999523162842
            },
            "health": 2,
            "blockScore": 2,
            "brickColor": {
                "r": 0.6556603908538818,
                "g": 0.027167143300175668,
                "b": 0.027167143300175668,
                "a": 1.0
            },
            "isDestroyed": false
        },
        {
            "position": {
                "x": 2.0197043418884279,
                "y": 1.159999966621399
            },
            "health": 1,
            "blockScore": 1,
            "brickColor": {
                "r": 0.8278301954269409,
                "g": 0.013583571650087834,
                "b": 0.013583571650087834,
                "a": 1.0
            },
            "isDestroyed": false
        },
        {
            "position": {
                "x": 2.0197043418884279,
                "y": 0.5199999809265137
            },
            "health": 0,
            "blockScore": 0,
            "brickColor": {
                "r": 1.0,
                "g": 0.0,
                "b": 0.0,
                "a": 1.0
            },
            "isDestroyed": false
        },
        {
            "position": {
                "x": 0.728879451751709,
                "y": 3.0799999237060549
            },
            "health": 3,
            "blockScore": 4,
            "brickColor": {
                "r": 0.31132078170776369,
                "g": 0.054334286600351337,
                "b": 0.054334286600351337,
                "a": 1.0
            },
            "isDestroyed": false
        },
        {
            "position": {
                "x": 0.728879451751709,
                "y": 2.440000057220459
            },
            "health": 3,
            "blockScore": 3,
            "brickColor": {
                "r": 0.48349058628082278,
                "g": 0.040750715881586078,
                "b": 0.040750715881586078,
                "a": 1.0
            },
            "isDestroyed": false
        },
        {
            "position": {
                "x": 0.728879451751709,
                "y": 1.7999999523162842
            },
            "health": 2,
            "blockScore": 2,
            "brickColor": {
                "r": 0.6556603908538818,
                "g": 0.027167143300175668,
                "b": 0.027167143300175668,
                "a": 1.0
            },
            "isDestroyed": false
        },
        {
            "position": {
                "x": 0.728879451751709,
                "y": 1.159999966621399
            },
            "health": 1,
            "blockScore": 1,
            "brickColor": {
                "r": 0.8278301954269409,
                "g": 0.013583571650087834,
                "b": 0.013583571650087834,
                "a": 1.0
            },
            "isDestroyed": false
        },
        {
            "position": {
                "x": -0.5619454383850098,
                "y": 3.0799999237060549
            },
            "health": 2,
            "blockScore": 4,
            "brickColor": {
                "r": 0.31132078170776369,
                "g": 0.054334286600351337,
                "b": 0.054334286600351337,
                "a": 1.0
            },
            "isDestroyed": false
        },
        {
            "position": {
                "x": -0.5619454383850098,
                "y": 2.440000057220459
            },
            "health": 3,
            "blockScore": 3,
            "brickColor": {
                "r": 0.48349058628082278,
                "g": 0.040750715881586078,
                "b": 0.040750715881586078,
                "a": 1.0
            },
            "isDestroyed": false
        },
        {
            "position": {
                "x": -0.5619454383850098,
                "y": 1.7999999523162842
            },
            "health": 2,
            "blockScore": 2,
            "brickColor": {
                "r": 0.6556603908538818,
                "g": 0.027167143300175668,
                "b": 0.027167143300175668,
                "a": 1.0
            },
            "isDestroyed": false
        },
        {
            "position": {
                "x": -0.5619454383850098,
                "y": 1.159999966621399
            },
            "health": 0,
            "blockScore": 1,
            "brickColor": {
                "r": 0.8278301954269409,
                "g": 0.013583571650087834,
                "b": 0.013583571650087834,
                "a": 1.0
            },
            "isDestroyed": false
        },
        {
            "position": {
                "x": -1.8527705669403077,
                "y": 3.0799999237060549
            },
            "health": 3,
            "blockScore": 4,
            "brickColor": {
                "r": 0.31132078170776369,
                "g": 0.054334286600351337,
                "b": 0.054334286600351337,
                "a": 1.0
            },
            "isDestroyed": false
        },
        {
            "position": {
                "x": -1.8527705669403077,
                "y": 2.440000057220459
            },
            "health": 3,
            "blockScore": 3,
            "brickColor": {
                "r": 0.48349058628082278,
                "g": 0.040750715881586078,
                "b": 0.040750715881586078,
                "a": 1.0
            },
            "isDestroyed": false
        },
        {
            "position": {
                "x": -1.8527705669403077,
                "y": 1.7999999523162842
            },
            "health": 2,
            "blockScore": 2,
            "brickColor": {
                "r": 0.6556603908538818,
                "g": 0.027167143300175668,
                "b": 0.027167143300175668,
                "a": 1.0
            },
            "isDestroyed": false
        },
        {
            "position": {
                "x": -1.8527705669403077,
                "y": 1.159999966621399
            },
            "health": 1,
            "blockScore": 1,
            "brickColor": {
                "r": 0.8278301954269409,
                "g": 0.013583571650087834,
                "b": 0.013583571650087834,
                "a": 1.0
            },
            "isDestroyed": false
        },
        {
            "position": {
                "x": -3.1435954570770265,
                "y": 3.0799999237060549
            },
            "health": 2,
            "blockScore": 4,
            "brickColor": {
                "r": 0.31132078170776369,
                "g": 0.054334286600351337,
                "b": 0.054334286600351337,
                "a": 1.0
            },
            "isDestroyed": false
        },
        {
            "position": {
                "x": -3.1435954570770265,
                "y": 2.440000057220459
            },
            "health": 3,
            "blockScore": 3,
            "brickColor": {
                "r": 0.48349058628082278,
                "g": 0.040750715881586078,
                "b": 0.040750715881586078,
                "a": 1.0
            },
            "isDestroyed": false
        },
        {
            "position": {
                "x": -3.1435954570770265,
                "y": 1.7999999523162842
            },
            "health": 2,
            "blockScore": 2,
            "brickColor": {
                "r": 0.6556603908538818,
                "g": 0.027167143300175668,
                "b": 0.027167143300175668,
                "a": 1.0
            },
            "isDestroyed": false
        },
        {
            "position": {
                "x": -3.1435954570770265,
                "y": 1.159999966621399
            },
            "health": 1,
            "blockScore": 1,
            "brickColor": {
                "r": 0.8278301954269409,
                "g": 0.013583571650087834,
                "b": 0.013583571650087834,
                "a": 1.0
            },
            "isDestroyed": false
        },
        {
            "position": {
                "x": -4.434420585632324,
                "y": 3.0799999237060549
            },
            "health": 2,
            "blockScore": 4,
            "brickColor": {
                "r": 0.31132078170776369,
                "g": 0.054334286600351337,
                "b": 0.054334286600351337,
                "a": 1.0
            },
            "isDestroyed": false
        },
        {
            "position": {
                "x": -4.434420585632324,
                "y": 2.440000057220459
            },
            "health": 3,
            "blockScore": 3,
            "brickColor": {
                "r": 0.48349058628082278,
                "g": 0.040750715881586078,
                "b": 0.040750715881586078,
                "a": 1.0
            },
            "isDestroyed": false
        },
        {
            "position": {
                "x": -4.434420585632324,
                "y": 1.7999999523162842
            },
            "health": 2,
            "blockScore": 2,
            "brickColor": {
                "r": 0.6556603908538818,
                "g": 0.027167143300175668,
                "b": 0.027167143300175668,
                "a": 1.0
            },
            "isDestroyed": false
        },
        {
            "position": {
                "x": -4.434420585632324,
                "y": 1.159999966621399
            },
            "health": 1,
            "blockScore": 1,
            "brickColor": {
                "r": 0.8278301954269409,
                "g": 0.013583571650087834,
                "b": 0.013583571650087834,
                "a": 1.0
            },
            "isDestroyed": false
        },
        {
            "position": {
                "x": -4.434420585632324,
                "y": 0.5199999809265137
            },
            "health": 0,
            "blockScore": 0,
            "brickColor": {
                "r": 1.0,
                "g": 0.0,
                "b": 0.0,
                "a": 1.0
            },
            "isDestroyed": false
        },
        {
            "position": {
                "x": -5.725245475769043,
                "y": 3.0799999237060549
            },
            "health": 4,
            "blockScore": 4,
            "brickColor": {
                "r": 0.31132078170776369,
                "g": 0.054334286600351337,
                "b": 0.054334286600351337,
                "a": 1.0
            },
            "isDestroyed": false
        },
        {
            "position": {
                "x": -5.725245475769043,
                "y": 2.440000057220459
            },
            "health": 2,
            "blockScore": 3,
            "brickColor": {
                "r": 0.48349058628082278,
                "g": 0.040750715881586078,
                "b": 0.040750715881586078,
                "a": 1.0
            },
            "isDestroyed": false
        },
        {
            "position": {
                "x": -5.725245475769043,
                "y": 1.7999999523162842
            },
            "health": 0,
            "blockScore": 2,
            "brickColor": {
                "r": 0.6556603908538818,
                "g": 0.027167143300175668,
                "b": 0.027167143300175668,
                "a": 1.0
            },
            "isDestroyed": false
        },
        {
            "position": {
                "x": -5.725245475769043,
                "y": 1.159999966621399
            },
            "health": 0,
            "blockScore": 1,
            "brickColor": {
                "r": 0.8278301954269409,
                "g": 0.013583571650087834,
                "b": 0.013583571650087834,
                "a": 1.0
            },
            "isDestroyed": false
        }
    ],
    "playerLives": 3,
    "score": 7,
    "Maxscore": 413,
    "level": 1,
    "blockisDestroyed": 7
}